README.md
setup.cfg
setup.py
searchlight_api/__init__.py
searchlight_api/analysis.py
searchlight_api/client.py
searchlight_api/errors.py
searchlight_api/utils.py
searchlight_api.egg-info/PKG-INFO
searchlight_api.egg-info/SOURCES.txt
searchlight_api.egg-info/dependency_links.txt
searchlight_api.egg-info/not-zip-safe
searchlight_api.egg-info/requires.txt
searchlight_api.egg-info/top_level.txt
searchlight_api/tests/integration/__init__.py
searchlight_api/tests/integration/client_integration_tests.py
searchlight_api/tests/unit/__init__.py
searchlight_api/tests/unit/analysis_tests.py
searchlight_api/tests/unit/client_tests.py
searchlight_api/tests/unit/utils_test.py