Metadata-Version: 2.1
Name: searchlight-api
Version: 1.0.0
Summary: A client to assist in connecting with the Conductor Searchlight API
Home-page: https://github.com/Conductor/searchlight-api-client-python
Author: Dan Goodman
Author-email: dgoodman@conductor.com
License: LICENSE
Platform: UNKNOWN
